{"id": 1278661, "homeID": 441, "awayID": 68, "season": "2021/2022", "status": "complete", "roundID": 70544, "game_week": 23, "revised_game_week": -1, "homeGoals": ["28"], "awayGoals": ["10", "32", "38", "51", "67"], "homeGoalCount": 1, "awayGoalCount": 5, "totalGoalCount": 6, "team_a_corners": 4, "team_b_corners": 3, "totalCornerCount": 7, "team_a_offsides": 3, "team_b_offsides": 0, "team_a_yellow_cards": 2, "team_b_yellow_cards": 1, "team_a_red_cards": 0, "team_b_red_cards": 0, "team_a_shotsOnTarget": 6, "team_b_shotsOnTarget": 3, "team_a_shotsOffTarget": 4, "team_b_shotsOffTarget": 9, "team_a_shots": 10, "team_b_shots": 12, "team_a_fouls": 17, "team_b_fouls": 9, "team_a_possession": 42, "team_b_possession": 58, "refereeID": 354, "coach_a_ID": 1022, "coach_b_ID": 156, "stadium_name": "Stade Pierre-Mauroy (Villeneuve d'Ascq)", "stadium_location": "", "team_a_cards_num": 2, "team_b_cards_num": 1, "odds_ft_1": 4.1, "odds_ft_x": 3.65, "odds_ft_2": 1.8, "odds_ft_over05": 1.03, "odds_ft_over15": 1.25, "odds_ft_over25": 1.7, "odds_ft_over35": 3.1, "odds_ft_over45": 5.5, "odds_ft_under05": 13, "odds_ft_under15": 3.75, "odds_ft_under25": 2, "odds_ft_under35": 1.38, "odds_ft_under45": 1.14, "odds_btts_yes": 1.7, "odds_btts_no": 2.05, "odds_team_a_cs_yes": 4.6, "odds_team_a_cs_no": 1.17, "odds_team_b_cs_yes": 2.6, "odds_team_b_cs_no": 1.43, "odds_doublechance_1x": 1.93, "odds_doublechance_12": 1.27, "odds_doublechance_x2": 1.24, "odds_1st_half_result_1": 4.33, "odds_1st_half_result_x": 2.25, "odds_1st_half_result_2": 2.5, "odds_2nd_half_result_1": 3.75, "odds_2nd_half_result_x": 2.55, "odds_2nd_half_result_2": 2.1, "odds_dnb_1": 0, "odds_dnb_2": 0, "odds_corners_over_75": 1.29, "odds_corners_over_85": 1.52, "odds_corners_over_95": 1.87, "odds_corners_over_105": 2.4, "odds_corners_over_115": 3.2, "odds_corners_under_75": 3.4, "odds_corners_under_85": 2.43, "odds_corners_under_95": 1.87, "odds_corners_under_105": 1.53, "odds_corners_under_115": 1.32, "odds_corners_1": 3.13, "odds_corners_x": 8.1, "odds_corners_2": 1.58, "odds_team_to_score_first_1": 2.63, "odds_team_to_score_first_x": 10.5, "odds_team_to_score_first_2": 1.53, "odds_win_to_nil_1": 7, "odds_win_to_nil_2": 3.1, "odds_1st_half_over05": 1.33, "odds_1st_half_over15": 2.63, "odds_1st_half_over25": 7, "odds_1st_half_over35": 19, "odds_1st_half_under05": 3.25, "odds_1st_half_under15": 1.44, "odds_1st_half_under25": 1.1, "odds_1st_half_under35": 1.02, "odds_2nd_half_over05": 1.21, "odds_2nd_half_over15": 1.95, "odds_2nd_half_over25": 4, "odds_2nd_half_over35": 9.25, "odds_2nd_half_under05": 4, "odds_2nd_half_under15": 1.73, "odds_2nd_half_under25": 1.21, "odds_2nd_half_under35": 1.05, "odds_btts_1st_half_yes": 0, "odds_btts_1st_half_no": 0, "odds_btts_2nd_half_yes": 0, "odds_btts_2nd_half_no": 0, "overallGoalCount": 6, "ht_goals_team_a": 1, "ht_goals_team_b": 3, "goals_2hg_team_a": 0, "goals_2hg_team_b": 2, "GoalCount_2hg": 2, "HTGoalCount": 4, "date_unix": 1644176700, "winningTeam": 68, "no_home_away": 0, "btts_potential": 72, "btts_fhg_potential": 33, "btts_2hg_potential": 14, "goalTimingDisabled": 0, "attendance": -1, "corner_timings_recorded": -1, "card_timings_recorded": 1, "team_a_fh_corners": -1, "team_b_fh_corners": -1, "team_a_2h_corners": -1, "team_b_2h_corners": -1, "corner_fh_count": -1, "corner_2h_count": -1, "team_a_fh_cards": 0, "team_b_fh_cards": 1, "team_a_2h_cards": 2, "team_b_2h_cards": 0, "total_fh_cards": 1, "total_2h_cards": 2, "attacks_recorded": -1, "team_a_dangerous_attacks": 0, "team_b_dangerous_attacks": 0, "team_a_attacks": 0, "team_b_attacks": 0, "team_a_xg": 0, "team_b_xg": 0, "total_xg": 0, "team_a_penalties_won": 0, "team_b_penalties_won": 0, "team_a_penalty_goals": 0, "team_b_penalty_goals": 0, "team_a_penalty_missed": 0, "team_b_penalty_missed": 0, "pens_recorded": 1, "goal_timings_recorded": 1, "team_a_0_10_min_goals": 0, "team_b_0_10_min_goals": 1, "team_a_corners_0_10_min": -1, "team_b_corners_0_10_min": -1, "team_a_cards_0_10_min": 0, "team_b_cards_0_10_min": 0, "throwins_recorded": -1, "team_a_throwins": -1, "team_b_throwins": -1, "freekicks_recorded": -1, "team_a_freekicks": -1, "team_b_freekicks": -1, "goalkicks_recorded": -1, "team_a_goalkicks": -1, "team_b_goalkicks": -1, "o45_potential": 9, "o35_potential": 24, "o25_potential": 48, "o15_potential": 91, "o05_potential": 91, "o15HT_potential": 53, "o05HT_potential": 86, "o05_2H_potential": 76, "o15_2H_potential": 23, "corners_potential": 10.5, "offsides_potential": 4.69, "cards_potential": 4.55, "avg_potential": 2.66, "home_url": "/clubs/lille-osc-metropole-441", "home_image": "teams/france-lille-osc-metropole.png", "home_name": "Lille", "away_url": "/clubs/paris-saint-germain-fc-68", "away_image": "teams/france-paris-saint-germain-fc.png", "away_name": "PSG", "home_ppg": 1.73, "away_ppg": 2.08, "pre_match_home_ppg": 1.9, "pre_match_away_ppg": 2, "pre_match_teamA_overall_ppg": 1.45, "pre_match_teamB_overall_ppg": 2.41, "u45_potential": 91, "u35_potential": 77, "u25_potential": 53, "u15_potential": 10, "u05_potential": 10, "corners_o85_potential": 62, "corners_o95_potential": 48, "corners_o105_potential": 38, "team_a_xg_prematch": 1.62, "team_b_xg_prematch": 1.83, "total_xg_prematch": 3.45, "match_url": "/france/paris-saint-germain-fc-vs-lille-osc-metropole-h2h-stats#1278661", "competition_id": 6019, "matches_completed_minimum": 23, "lineups": {"team_a": [{"player_id": 66198, "shirt_number": 1, "player_events": []}, {"player_id": 461790, "shirt_number": 6, "player_events": []}, {"player_id": 40023, "shirt_number": 2, "player_events": [{"event_type": "Yellow", "event_time": "75"}]}, {"player_id": 26555, "shirt_number": 5, "player_events": []}, {"player_id": 184909, "shirt_number": 4, "player_events": [{"event_type": "Goal", "event_time": "28"}]}, {"player_id": 3348, "shirt_number": 11, "player_events": []}, {"player_id": 17380, "shirt_number": 21, "player_events": []}, {"player_id": 184723, "shirt_number": 24, "player_events": []}, {"player_id": 17562, "shirt_number": 7, "player_events": []}, {"player_id": 112935, "shirt_number": 22, "player_events": []}, {"player_id": 171435, "shirt_number": 9, "player_events": []}], "team_b": [{"player_id": 18044, "shirt_number": 50, "player_events": []}, {"player_id": 466266, "shirt_number": 5, "player_events": []}, {"player_id": 2976, "shirt_number": 3, "player_events": [{"event_type": "Goal", "event_time": "32"}]}, {"player_id": 10797, "shirt_number": 2, "player_events": []}, {"player_id": 668543, "shirt_number": 25, "player_events": []}, {"player_id": 461916, "shirt_number": 11, "player_events": []}, {"player_id": 2958, "shirt_number": 6, "player_events": []}, {"player_id": 2904, "shirt_number": 15, "player_events": [{"event_type": "Goal", "event_time": "10"}, {"event_type": "Goal", "event_time": "51"}]}, {"player_id": 2928, "shirt_number": 8, "player_events": [{"event_type": "Yellow", "event_time": "45+1"}]}, {"player_id": 460830, "shirt_number": 30, "player_events": [{"event_type": "Goal", "event_time": "38"}]}, {"player_id": 471122, "shirt_number": 7, "player_events": [{"event_type": "Goal", "event_time": "67"}]}]}, "bench": {"team_a": [{"player_in_id": 66728, "player_in_shirt_number": 29, "player_out_id": 112935, "player_out_time": " 70'", "player_in_events": [{"event_type": "Yellow", "event_time": "83'"}]}, {"player_in_id": 4401, "player_in_shirt_number": 20, "player_out_id": 3348, "player_out_time": " 70'", "player_in_events": []}, {"player_in_id": 40400, "player_in_shirt_number": 23, "player_out_id": 17562, "player_out_time": " 85'", "player_in_events": []}, {"player_in_id": 24603, "player_in_shirt_number": 30, "player_out_id": -1, "player_out_time": "-1", "player_in_events": []}, {"player_in_id": 469265, "player_in_shirt_number": 8, "player_out_id": -1, "player_out_time": "-1", "player_in_events": []}, {"player_in_id": 4078, "player_in_shirt_number": 26, "player_out_id": -1, "player_out_time": "-1", "player_in_events": []}, {"player_in_id": 757974, "player_in_shirt_number": 34, "player_out_id": -1, "player_out_time": "-1", "player_in_events": []}, {"player_in_id": 39716, "player_in_shirt_number": 3, "player_out_id": -1, "player_out_time": "-1", "player_in_events": []}], "team_b": [{"player_in_id": 1137, "player_in_shirt_number": 23, "player_out_id": 461916, "player_out_time": " 45'", "player_in_events": []}, {"player_in_id": 1415, "player_in_shirt_number": 24, "player_out_id": 2976, "player_out_time": " 78'", "player_in_events": []}, {"player_in_id": 638035, "player_in_shirt_number": 34, "player_out_id": 2928, "player_out_time": " 85'", "player_in_events": []}, {"player_in_id": 50965, "player_in_shirt_number": 17, "player_out_id": -1, "player_out_time": "-1", "player_in_events": []}, {"player_in_id": 462769, "player_in_shirt_number": 1, "player_out_id": -1, "player_out_time": "-1", "player_in_events": []}, {"player_in_id": 3318, "player_in_shirt_number": 20, "player_out_id": -1, "player_out_time": "-1", "player_in_events": []}, {"player_in_id": 194016, "player_in_shirt_number": 28, "player_out_id": -1, "player_out_time": "-1", "player_in_events": []}, {"player_in_id": 708348, "player_in_shirt_number": 38, "player_out_id": -1, "player_out_time": "-1", "player_in_events": []}, {"player_in_id": 466851, "player_in_shirt_number": 14, "player_out_id": -1, "player_out_time": "-1", "player_in_events": []}]}, "team_a_goal_details": [{"player_id": 184909, "time": "28", "extra": null, "assist_player_id": 3348}], "team_b_goal_details": [{"player_id": 2904, "time": "10", "extra": null, "assist_player_id": -1}, {"player_id": 2976, "time": "32", "extra": null, "assist_player_id": 460830}, {"player_id": 460830, "time": "38", "extra": null, "assist_player_id": -1}, {"player_id": 2904, "time": "51", "extra": null, "assist_player_id": 2928}, {"player_id": 471122, "time": "67", "extra": null, "assist_player_id": 2958}], "trends": {"home": [["chart", "Coming into this game, Lille has picked up 8 points from the last 5 games, both home and away. That's 1.6 points per game on average. BTTS has landed in an intriguing 3 of those games. Lille has scored 7 times in the last 5 fixtures."], ["great", "Superb stuff from Lille at home, where they are currently unbeaten in 9 games. Can they go another game without defeat?"], ["great", "It's possible we will see a couple of goals here, with the last 4 games for Lille ending with 2 goals or more being scored."], ["great", "Lille will be looking to keep up the momentum today against PSG, having lost just 1 game from the last 5. They have won 2 and drawn 2"], ["bad", "Things have not been going that well in front of goal for Lille recently, with the side failing to score in 2 of the last 5 games. Will the manager change his tactics today, or throw in another forward?"], ["great", "In the last 5 matches for Lille, 3 of those games has ended with both teams scoring. This season 16 matches (73% of all matches) involving Lille has seen BTTS landing."]], "away": [["chart", "Coming into this game, PSG has picked up 11 points from the last 5 games, both home and away. That's 2.2 points per game on average. BTTS has landed in just 2 of those games. PSG has scored 10 times in the last 5 fixtures."], ["great", "Superb stuff from PSG away from home, where they are currently unbeaten in 6 games. Can they go another game without defeat?"], ["great", "Scoring is not an issue for PSG when they play away from home. They have scored in the last 5 games they have played on the road. Can Lille stop this run?"], ["great", "Momentum is really building for PSG as they have now gone 13 games without losing. They have won 3 of the last 5 games they have played."], ["great", "It's possible we will see a couple of goals here, with the last 6 games for PSG ending with 2 goals or more being scored."], ["great", "PSG has kept 3 clean sheets in the last 5 games, conceding 2 goals during this period. Overall this season, their defence has kept a clean sheet on 8 occasions."], ["great", "PSG is unbeaten in the last 5 games coming into this fixture against Lille, having won 3 and drawn 2. They have scored 10 goals in those 5 games."], ["bad", "Just 2 of the last 5 games for PSG has ended with both teams scoring. They have won 3 of those 5 games. Overall, BTTS has landed in 13/22 games for PSG this season."], ["great", "It's likely that PSG will score today, as they have netted in the last 6 games coming into this one and have scored 10 goals in the last five games."]]}, "team_a_card_details": [{"player_id": 40023, "card_type": "Yellow", "time": "75"}, {"player_id": 66728, "card_type": "Yellow", "time": "83'"}], "team_b_card_details": [{"player_id": 2928, "card_type": "Yellow", "time": "45+1"}], "h2h": {"team_a_id": 441, "team_b_id": 68, "previous_matches_results": {"team_a_win_home": 4, "team_a_win_away": 2, "team_b_win_home": 9, "team_b_win_away": 6, "draw": 7, "team_a_wins": 6, "team_b_wins": 15, "totalMatches": 28, "team_a_win_percent": 21, "team_b_win_percent": 54}, "betting_stats": {"over05": 24, "over15": 18, "over25": 15, "over35": 7, "over45": 2, "over55": 2, "btts": 13, "clubACS": 7, "clubBCS": 12, "over05Percentage": 86, "over15Percentage": 64, "over25Percentage": 54, "over35Percentage": 25, "over45Percentage": 7, "over55Percentage": 7, "bttsPercentage": 46, "clubACSPercentage": 25, "clubBCSPercentage": 43, "avg_goals": 2.46, "total_goals": 69}, "previous_matches_ids": [{"id": 1278558, "date_unix": 1635534000, "team_a_id": 68, "team_b_id": 441, "team_a_goals": 2, "team_b_goals": 1}, {"id": 1265036, "date_unix": 1627840800, "team_a_id": 441, "team_b_id": 68, "team_a_goals": 1, "team_b_goals": 0}, {"id": 1016197, "date_unix": 1617462000, "team_a_id": 68, "team_b_id": 441, "team_a_goals": 0, "team_b_goals": 1}, {"id": 1195658, "date_unix": 1615999500, "team_a_id": 68, "team_b_id": 441, "team_a_goals": 3, "team_b_goals": 0}, {"id": 1016048, "date_unix": 1608494400, "team_a_id": 441, "team_b_id": 68, "team_a_goals": 0, "team_b_goals": 0}, {"id": 646468, "date_unix": 1580068800, "team_a_id": 441, "team_b_id": 68, "team_a_goals": 0, "team_b_goals": 2}, {"id": 646391, "date_unix": 1574451900, "team_a_id": 68, "team_b_id": 441, "team_a_goals": 2, "team_b_goals": 0}, {"id": 420243, "date_unix": 1555268400, "team_a_id": 441, "team_b_id": 68, "team_a_goals": 5, "team_b_goals": 1}, {"id": 420047, "date_unix": 1541187900, "team_a_id": 68, "team_b_id": 441, "team_a_goals": 2, "team_b_goals": 1}, {"id": 55928, "date_unix": 1517673600, "team_a_id": 441, "team_b_id": 68, "team_a_goals": 0, "team_b_goals": 3}, {"id": 55864, "date_unix": 1512835200, "team_a_id": 68, "team_b_id": 441, "team_a_goals": 3, "team_b_goals": 1}, {"id": 22439, "date_unix": 1486497600, "team_a_id": 68, "team_b_id": 441, "team_a_goals": 2, "team_b_goals": 1}, {"id": 22309, "date_unix": 1477680300, "team_a_id": 441, "team_b_id": 68, "team_a_goals": 0, "team_b_goals": 1}, {"id": 26078, "date_unix": 1455379200, "team_a_id": 68, "team_b_id": 441, "team_a_goals": 0, "team_b_goals": 0}, {"id": 25827, "date_unix": 1438972200, "team_a_id": 441, "team_b_id": 68, "team_a_goals": 0, "team_b_goals": 1}, {"id": 22919, "date_unix": 1429974000, "team_a_id": 68, "team_b_id": 441, "team_a_goals": 6, "team_b_goals": 1}, {"id": 22746, "date_unix": 1417636800, "team_a_id": 441, "team_b_id": 68, "team_a_goals": 1, "team_b_goals": 1}, {"id": 23333, "date_unix": 1399748400, "team_a_id": 441, "team_b_id": 68, "team_a_goals": 1, "team_b_goals": 3}, {"id": 23157, "date_unix": 1387742400, "team_a_id": 68, "team_b_id": 441, "team_a_goals": 2, "team_b_goals": 2}, {"id": 890031, "date_unix": 1359316800, "team_a_id": 68, "team_b_id": 441, "team_a_goals": 1, "team_b_goals": 0}, {"id": 889538, "date_unix": 1346612400, "team_a_id": 441, "team_b_id": 68, "team_a_goals": 1, "team_b_goals": 2}, {"id": 1095337, "date_unix": 1335726000, "team_a_id": 441, "team_b_id": 68, "team_a_goals": 2, "team_b_goals": 1}, {"id": 1095178, "date_unix": 1324238400, "team_a_id": 68, "team_b_id": 441, "team_a_goals": 0, "team_b_goals": 0}, {"id": 898171, "date_unix": 1306004400, "team_a_id": 68, "team_b_id": 441, "team_a_goals": 2, "team_b_goals": 2}, {"id": 891691, "date_unix": 1305398700, "team_a_id": 68, "team_b_id": 441, "team_a_goals": 0, "team_b_goals": 1}, {"id": 897531, "date_unix": 1281898800, "team_a_id": 441, "team_b_id": 68, "team_a_goals": 0, "team_b_goals": 0}, {"id": 899158, "date_unix": 1263672000, "team_a_id": 441, "team_b_id": 68, "team_a_goals": 3, "team_b_goals": 1}, {"id": 898860, "date_unix": 1251644400, "team_a_id": 68, "team_b_id": 441, "team_a_goals": 3, "team_b_goals": 0}]}, "tv_stations": ["1xBet", "1xBet.kz", "1xStavka.ru", "Amazon Prime Video (Fra)", "Arena Sport (Cro)", "Arena Sport (Svn)", "bet365", "bet365.ru", "Betclic.pl", "BT Sport", "Chance", "DAZN Deutsch", "Diema Sport 2", "Digi Sport 1 (Hun)", "Eleven Sports (Por)", "Eleven Sports 2 (Pol)", "Fortuna", "Fortuna PL", "Fortuna SK", "Nova Sport 2 (Cze)", "Nova Sports (Hel)", "nSport+", "Setanta Sports Eurasia", "Sport 2 (Cze)", "STS.pl", "Tipsport", "Tipsport SK", "Wplay", "Ziggo Sport Voetbal"], "weather": null, "odds_comparison": {"FT Result": {"1": {"bet365": "5.25", "10Bet": "4.95", "BetClic": "5.05", "Pncl": "5.52", "bwin": "5.00", "CloudBet": "91.35", "Sbo": "4.36", "1xbet": "5.75", "BetRegal": "3.85", "MansionBet": "5.25", "Ladbrokes": "5.00", "Coral": "5.00", "Intertops": "5.25", "Dafabet": "5.00", "888Sport": "5.40", "Nitrogen Sports": "4.86", "Betfair": "4.75", "Unibet": "4.00", "WilliamHill": "5.00", "NordicBet": "4.90", "Marathon": "5.50", "Betsson": "4.90", "188Bet": "4.95", "Sportingbet": "5.00", "Betway": "4.75", "Tipico": "5.30", "BetCRIS": "5.00", "ComeOn": "5.25", "HKJC": "40.00", "Interwetten": "4.00", "Cashpoint": "5.04", "BetVictor": "5.50", "TitanBet": "4.20"}, "X": {"bet365": "3.80", "10Bet": "4.05", "BetClic": "4.05", "Pncl": "4.15", "bwin": "3.90", "CloudBet": "19.45", "Sbo": "4.07", "1xbet": "3.86", "BetRegal": "3.70", "MansionBet": "4.15", "Ladbrokes": "3.90", "Coral": "3.90", "Intertops": "3.90", "Dafabet": "4.10", "888Sport": "3.95", "Nitrogen Sports": "3.79", "Betfair": "3.80", "Unibet": "3.60", "WilliamHill": "4.00", "NordicBet": "4.10", "Marathon": "4.30", "Betsson": "4.10", "188Bet": "3.95", "Sportingbet": "3.90", "Betway": "4.20", "Tipico": "4.10", "BetCRIS": "4.03", "ComeOn": "4.20", "HKJC": "14.00", "Interwetten": "3.65", "Cashpoint": "3.90", "BetVictor": "4.00", "TitanBet": "3.80"}, "2": {"bet365": "1.65", "10Bet": "1.64", "BetClic": "1.63", "Pncl": "1.65", "bwin": "1.66", "CloudBet": "1.04", "Sbo": "1.64", "1xbet": "1.64", "BetRegal": "1.90", "MansionBet": "1.64", "Ladbrokes": "1.67", "Coral": "1.67", "Intertops": "1.60", "Dafabet": "1.69", "888Sport": "1.60", "Nitrogen Sports": "1.66", "Betfair": "1.60", "Unibet": "1.89", "WilliamHill": "1.65", "NordicBet": "1.65", "Marathon": "1.70", "Betsson": "1.65", "188Bet": "1.68", "Sportingbet": "1.66", "Betway": "1.67", "Tipico": "1.60", "BetCRIS": "1.63", "ComeOn": "1.60", "HKJC": "1.03", "Interwetten": "1.90", "Cashpoint": "1.68", "BetVictor": "1.62", "TitanBet": "1.85"}}, "Over/Under": {"Over 2.5": {"BetClic": 1.72, "1xbet": "1.70", "Ladbrokes": 1.67, "Coral": 1.67, "Intertops": 1.7, "888Sport": 1.74, "Unibet": 1.74, "NordicBet": "1.75", "WilliamHill": "1.73", "Marathon": "1.79", "Betsson": "1.75", "Sportingbet": "1.75", "Betway": "1.70", "Tipico": "1.67", "BetCRIS": "1.72", "ComeOn": "1.72", "Cashpoint": 1.78, "BetVictor": 1.7}, "Under 2.5": {"BetClic": 2.09, "1xbet": "2.28", "Ladbrokes": 2.05, "Coral": 2.1, "Intertops": 2, "888Sport": 2.08, "Unibet": 2.08, "NordicBet": "2.10", "WilliamHill": "2.00", "Marathon": "2.25", "Betsson": "2.10", "Sportingbet": "1.98", "Betway": "2.05", "Tipico": "2.15", "BetCRIS": "2.09", "ComeOn": "2.11", "Cashpoint": 1.97, "BetVictor": 2.15}, "Over 0.5": {"1xbet": "1.03", "NordicBet": "1.03", "WilliamHill": "1.05", "Marathon": "1.01", "Betsson": "1.03", "Sportingbet": "1.05", "BetCRIS": "1.04", "ComeOn": "1.02"}, "Under 0.5": {"1xbet": "14.10", "NordicBet": "13.00", "WilliamHill": "9.00", "Marathon": "11.50", "Betsson": "13.00", "Sportingbet": "10.50", "BetCRIS": "14.75", "ComeOn": "14.00"}, "Over 1.5": {"1xbet": "1.21", "NordicBet": "1.24", "WilliamHill": "1.25", "Marathon": "1.22", "Betsson": "1.24", "Sportingbet": "1.25", "Betway": "1.22", "Tipico": "1.20", "BetCRIS": "1.23", "ComeOn": "1.23"}, "Under 1.5": {"1xbet": "4.71", "NordicBet": "4.20", "WilliamHill": "3.75", "Marathon": "4.10", "Betsson": "4.20", "Sportingbet": "3.70", "Betway": "4.20", "Tipico": "4.30", "BetCRIS": "4.08", "ComeOn": "4.20"}, "Over 3.5": {"1xbet": "2.65", "NordicBet": "2.90", "WilliamHill": "2.75", "Marathon": "2.74", "Betsson": "2.90", "Sportingbet": "2.80", "Betway": "2.62", "Tipico": "2.65", "BetCRIS": "2.76", "ComeOn": "2.80"}, "Under 3.5": {"1xbet": "1.50", "NordicBet": "1.42", "WilliamHill": "1.40", "Marathon": "1.43", "Betsson": "1.42", "Sportingbet": "1.38", "Betway": "1.42", "Tipico": "1.45", "BetCRIS": "1.43", "ComeOn": "1.44"}, "Under 4.5": {"1xbet": "1.19", "NordicBet": "1.16", "WilliamHill": "1.14", "Marathon": "1.14", "Betsson": "1.16", "Sportingbet": "1.14", "Betway": "1.17", "Tipico": "1.17", "BetCRIS": "1.16", "ComeOn": "1.17"}, "Over 4.5": {"1xbet": "5.01", "NordicBet": "5.50", "WilliamHill": "5.00", "Marathon": "4.80", "Betsson": "5.50", "Sportingbet": "5.25", "Betway": "5.00", "Tipico": "4.70", "BetCRIS": "5.00", "ComeOn": "5.00"}}, "Result 1st Half": {"1": {"bet365": "5.00", "bwin": "4.80", "NordicBet": "5.00", "WilliamHill": "4.80", "Marathon": "5.20", "Unibet": "4.25", "Betsson": "5.00", "188Bet": "4.75", "Pncl": "5.30", "Sbo": "4.90", "1xbet": "5.65", "Sportingbet": "4.80", "Betway": "5.00", "Tipico": "5.20", "BetCRIS": "5.00", "888Sport": "5.10", "Dafabet": "4.55", "10Bet": "4.80", "ComeOn": "5.00"}, "X": {"bet365": "2.38", "bwin": "2.25", "NordicBet": "2.35", "WilliamHill": "2.10", "Marathon": "2.36", "Unibet": "2.23", "Betsson": "2.35", "188Bet": "2.19", "Pncl": "2.43", "Sbo": "2.28", "1xbet": "2.44", "Sportingbet": "2.25", "Betway": "2.30", "Tipico": "2.35", "BetCRIS": "2.30", "888Sport": "2.38", "Dafabet": "2.24", "10Bet": "2.25", "ComeOn": "2.25"}, "2": {"bet365": "2.20", "bwin": "2.20", "NordicBet": "2.20", "WilliamHill": "2.25", "Marathon": "2.18", "Unibet": "2.45", "Betsson": "2.20", "188Bet": "2.31", "Pncl": "2.31", "Sbo": "2.28", "1xbet": "2.17", "Sportingbet": "2.20", "Betway": "2.15", "Tipico": "2.05", "BetCRIS": "2.10", "888Sport": "2.08", "Dafabet": "2.31", "10Bet": "2.15", "ComeOn": "2.15"}}, "Over/Under 2nd Half": {"Over 0.5": {"bwin": "1.20", "NordicBet": "1.20", "WilliamHill": "1.25", "Marathon": "1.20", "Unibet": "1.18", "Betsson": "1.20", "1xbet": "1.19", "Sportingbet": "1.20", "Betway": "1.20", "Tipico": "1.17", "BetCRIS": "1.16", "888Sport": "1.18"}, "Under 0.5": {"bwin": "4.10", "NordicBet": "4.50", "WilliamHill": "3.75", "Marathon": "4.55", "Unibet": "4.40", "Betsson": "4.50", "1xbet": "4.74", "Sportingbet": "4.10", "Betway": "4.00", "Tipico": "4.30", "BetCRIS": "4.90", "888Sport": "4.40"}, "Over 1.5": {"bwin": "1.95", "NordicBet": "1.95", "WilliamHill": "2.00", "Marathon": "1.94", "Unibet": "1.95", "Betsson": "1.95", "1xbet": "1.81", "Sportingbet": "1.95", "Betway": "1.91", "Tipico": "1.80", "BetCRIS": "1.88", "888Sport": "1.95", "10Bet": "1.90", "ComeOn": "1.90"}, "Under 1.5": {"bwin": "1.75", "NordicBet": "1.83", "WilliamHill": "1.73", "Marathon": "1.86", "Unibet": "1.76", "Betsson": "1.83", "1xbet": "1.99", "Sportingbet": "1.75", "Betway": "1.80", "Tipico": "1.90", "BetCRIS": "1.78", "888Sport": "1.76", "10Bet": "1.83", "ComeOn": "1.83"}, "Over 2.5": {"bwin": "4.00", "NordicBet": "4.00", "WilliamHill": "4.00", "Marathon": "3.95", "Unibet": "4.20", "Betsson": "4.00", "1xbet": "3.63", "Sportingbet": "4.00", "Betway": "3.60", "Tipico": "3.50", "BetCRIS": "3.50", "888Sport": "4.20"}, "Under 2.5": {"bwin": "1.21", "NordicBet": "1.24", "WilliamHill": "1.22", "Marathon": "1.25", "Unibet": "1.19", "Betsson": "1.24", "1xbet": "1.29", "Sportingbet": "1.21", "Betway": "1.25", "Tipico": "1.25", "BetCRIS": "1.20", "888Sport": "1.19"}}, "Double Chance": {"1X": {"bwin": "2.20", "NordicBet": "2.30", "WilliamHill": "1.91", "Marathon": "2.38", "Unibet": "1.91", "Betsson": "2.30", "Sbo": "2.23", "1xbet": "2.34", "Sportingbet": "2.20", "Betway": "2.20", "Tipico": "2.25", "BetCRIS": "2.20", "888Sport": "2.38", "Pncl": "2.38", "10Bet": "2.30", "ComeOn": "2.25"}, "12": {"bwin": "1.25", "NordicBet": "1.20", "WilliamHill": "1.29", "Marathon": "1.29", "Unibet": "1.29", "Betsson": "1.20", "Sbo": "1.22", "1xbet": "1.29", "Sportingbet": "1.25", "Betway": "1.25", "Tipico": "1.25", "BetCRIS": "1.23", "888Sport": "1.23", "Pncl": "1.26", "10Bet": "1.25", "ComeOn": "1.23"}, "X2": {"bwin": "1.18", "NordicBet": "1.17", "WilliamHill": "1.22", "Marathon": "1.21", "Unibet": "1.24", "Betsson": "1.17", "Sbo": "1.17", "1xbet": "1.16", "Sportingbet": "1.18", "Betway": "1.18", "Tipico": "1.13", "BetCRIS": "1.17", "888Sport": "1.15", "Pncl": "1.17", "10Bet": "1.19", "ComeOn": "1.17"}}, "Team To Score First": {"1": {"bet365": "2.75", "Marathon": "2.97", "Betway": "2.80", "Tipico": "2.80", "BetCRIS": "2.70", "10Bet": "2.75", "ComeOn": "2.95"}, "2": {"bet365": "1.50", "Marathon": "1.54", "Betway": "1.53", "Tipico": "1.50", "BetCRIS": "1.48", "10Bet": "1.47", "ComeOn": "1.48"}, "X": {"Marathon": "11.50", "Betway": "11.00", "Tipico": "12.00", "BetCRIS": "15.00", "10Bet": "13.00", "ComeOn": "12.00"}}, "Result 2nd Half": {"1": {"bet365": "4.50", "bwin": "4.50", "NordicBet": "4.50", "WilliamHill": "4.40", "Marathon": "4.80", "Unibet": "3.90", "Betsson": "4.50", "1xbet": "5.24", "Sportingbet": "4.50", "Betway": "4.50", "BetCRIS": "4.60", "888Sport": "4.90", "10Bet": "4.50", "ComeOn": "4.70"}, "2": {"bet365": "1.91", "bwin": "1.95", "NordicBet": "1.98", "WilliamHill": "2.00", "Marathon": "1.98", "Unibet": "2.20", "Betsson": "1.98", "1xbet": "1.95", "Sportingbet": "1.95", "Betway": "2.00", "BetCRIS": "1.90", "888Sport": "1.88", "10Bet": "1.95", "ComeOn": "1.95"}, "X": {"bwin": "2.65", "NordicBet": "2.75", "WilliamHill": "2.50", "Marathon": "2.77", "Unibet": "2.60", "Betsson": "2.75", "1xbet": "2.91", "Sportingbet": "2.65", "Betway": "2.63", "BetCRIS": "2.75", "888Sport": "2.70", "10Bet": "2.60", "ComeOn": "2.65"}}, "Over/Under 1st Half": {"Over 0.5": {"bet365": "1.33", "bwin": "1.34", "NordicBet": "1.36", "WilliamHill": "1.40", "Marathon": "1.33", "Unibet": "1.30", "Betsson": "1.36", "Pncl": "1.36", "1xbet": "1.31", "Sportingbet": "1.34", "Betway": "1.33", "Tipico": "1.30", "BetCRIS": "1.32", "888Sport": "1.28", "Dafabet": "1.34"}, "Over 1.5": {"bet365": "2.50", "bwin": "2.50", "NordicBet": "2.60", "WilliamHill": "2.62", "Marathon": "2.53", "Unibet": "2.55", "Betsson": "2.60", "Pncl": "2.72", "1xbet": "2.45", "Sportingbet": "2.50", "Betway": "2.50", "Tipico": "2.45", "BetCRIS": "2.50", "888Sport": "2.55", "Dafabet": "2.40"}, "Over 2.5": {"bet365": "6.50", "bwin": "6.25", "NordicBet": "6.00", "WilliamHill": "6.00", "Marathon": "6.10", "Unibet": "6.75", "Betsson": "6.00", "1xbet": "6.48", "Sportingbet": "6.25", "Betway": "5.50", "Tipico": "5.20", "BetCRIS": "6.25", "888Sport": "6.50"}, "Under 0.5": {"bet365": "3.25", "bwin": "2.95", "NordicBet": "3.25", "WilliamHill": "2.75", "Marathon": "3.32", "Unibet": "3.20", "Betsson": "3.25", "Pncl": "3.35", "1xbet": "3.57", "Sportingbet": "2.95", "Betway": "3.00", "Tipico": "3.20", "BetCRIS": "3.15", "888Sport": "3.30", "Dafabet": "3.27"}, "Under 1.5": {"bet365": "1.50", "bwin": "1.46", "NordicBet": "1.48", "WilliamHill": "1.44", "Marathon": "1.52", "Unibet": "1.45", "Betsson": "1.48", "Pncl": "1.51", "1xbet": "1.58", "Sportingbet": "1.46", "Betway": "1.48", "Tipico": "1.47", "BetCRIS": "1.48", "888Sport": "1.45", "Dafabet": "1.61"}, "Under 2.5": {"bet365": "1.11", "bwin": "1.10", "NordicBet": "1.12", "WilliamHill": "1.11", "Marathon": "1.12", "Unibet": "1.09", "Betsson": "1.12", "1xbet": "1.13", "Sportingbet": "1.10", "Betway": "1.11", "Tipico": "1.12", "BetCRIS": "1.11", "888Sport": "1.10"}}, "Clean Sheet - Home": {"Yes": {"bwin": "5.25", "Sportingbet": "5.25", "Betway": "5.25"}, "No": {"bwin": "1.15", "Sportingbet": "1.15", "Betway": "1.13"}}, "Both Teams To Score": {"Yes": {"bet365": "1.75", "bwin": "1.78", "NordicBet": "1.75", "WilliamHill": "1.70", "Marathon": "1.71", "Unibet": "1.64", "Betsson": "1.75", "1xbet": "1.66", "Sportingbet": "1.78", "Betway": "1.78", "Tipico": "1.65", "BetCRIS": "1.72", "888Sport": "1.77", "Pncl": "1.76", "10Bet": "1.68", "ComeOn": "1.68"}, "No": {"bet365": "2.00", "bwin": "1.93", "NordicBet": "2.05", "WilliamHill": "2.05", "Marathon": "2.14", "Unibet": "2.20", "Betsson": "2.05", "1xbet": "2.22", "Sportingbet": "1.93", "Betway": "2.00", "Tipico": "2.10", "BetCRIS": "2.00", "888Sport": "2.00", "Pncl": "2.14", "10Bet": "2.10", "ComeOn": "2.10"}}, "BTTS 1st Half": {"Yes": {"bet365": "4.33", "bwin": "4.33", "WilliamHill": "4.00", "Marathon": "4.20", "Unibet": "4.25", "1xbet": "3.95", "Sportingbet": "4.33", "Betway": "4.00", "Tipico": "4.00", "BetCRIS": "4.20", "888Sport": "4.60", "Pncl": "4.60"}, "No": {"bet365": "1.20", "bwin": "1.19", "WilliamHill": "1.22", "Marathon": "1.23", "Unibet": "1.20", "1xbet": "1.25", "Sportingbet": "1.19", "Betway": "1.20", "Tipico": "1.20", "BetCRIS": "1.19", "888Sport": "1.17", "Pncl": "1.20"}}, "BTTS 2nd Half": {"Yes": {"bet365": "3.25", "bwin": "3.25", "NordicBet": "3.10", "WilliamHill": "3.00", "Marathon": "3.15", "Unibet": "3.35", "Betsson": "3.10", "1xbet": "3.03", "Sportingbet": "3.25", "Betway": "3.00", "Tipico": "3.00", "888Sport": "3.35"}, "No": {"bet365": "1.33", "bwin": "1.30", "NordicBet": "1.33", "WilliamHill": "1.36", "Marathon": "1.36", "Unibet": "1.27", "Betsson": "1.33", "1xbet": "1.39", "Sportingbet": "1.30", "Betway": "1.33", "Tipico": "1.33", "888Sport": "1.27"}}, "Win To Nil": {"1": {"WilliamHill": "7.00", "Betway": "7.50"}, "2": {"WilliamHill": "3.10", "Betway": "2.88"}}, "Corners Over Under": {"Over 7.5": {"1xbet": "1.31", "Marathon": "1.24", "Betway": "1.30", "888Sport": "1.29", "Unibet": "1.29", "Sportingbet": "1.24", "bwin": "1.24", "NordicBet": "1.32", "Betsson": "1.32"}, "Under 7.5": {"1xbet": "3.49", "Marathon": "3.64", "Betway": "3.20", "888Sport": "3.40", "Unibet": "3.40", "Sportingbet": "3.60", "bwin": "3.60", "NordicBet": "3.20", "Betsson": "3.20"}, "Under 8.5": {"1xbet": "2.61", "Pncl": "2.62", "Marathon": "2.60", "Betway": "2.30", "888Sport": "2.40", "Unibet": "2.40", "Sportingbet": "2.45", "bwin": "2.45", "NordicBet": "2.30", "Betsson": "2.30"}, "Over 8.5": {"1xbet": "1.46", "Pncl": "1.50", "Marathon": "1.47", "Betway": "1.55", "888Sport": "1.53", "Unibet": "1.53", "Sportingbet": "1.46", "bwin": "1.46", "NordicBet": "1.57", "Betsson": "1.57"}, "Under 9.5": {"1xbet": "1.96", "Pncl": "2.00", "Marathon": "1.95", "Betway": "1.85", "888Sport": "1.82", "Unibet": "1.82", "10Bet": "1.90", "ComeOn": "1.90", "Sportingbet": "1.85", "bwin": "1.85", "NordicBet": "1.83", "Betsson": "1.83", "Tipico": "1.80"}, "Over 9.5": {"1xbet": "1.84", "Pncl": "1.84", "Marathon": "1.85", "Betway": "1.85", "888Sport": "1.92", "Unibet": "1.92", "10Bet": "1.83", "ComeOn": "1.83", "Sportingbet": "1.80", "bwin": "1.80", "NordicBet": "1.92", "Betsson": "1.92", "Tipico": "1.90"}, "Over 10.5": {"1xbet": "2.27", "Pncl": "2.45", "Marathon": "2.36", "Betway": "2.30", "888Sport": "2.55", "Unibet": "2.55", "Sportingbet": "2.37", "bwin": "2.37", "NordicBet": "2.45", "Betsson": "2.45"}, "Under 10.5": {"1xbet": "1.59", "Pncl": "1.56", "Marathon": "1.56", "Betway": "1.55", "888Sport": "1.48", "Unibet": "1.48", "Sportingbet": "1.49", "bwin": "1.49", "NordicBet": "1.52", "Betsson": "1.52"}, "Under 11.5": {"1xbet": "1.34", "Marathon": "1.31", "Betway": "1.33", "888Sport": "1.27", "Unibet": "1.27", "Sportingbet": "1.27", "bwin": "1.27", "NordicBet": "1.30", "Betsson": "1.30"}, "Over 11.5": {"1xbet": "3.11", "Marathon": "3.14", "Betway": "3.00", "888Sport": "3.50", "Unibet": "3.50", "Sportingbet": "3.30", "bwin": "3.30", "NordicBet": "3.30", "Betsson": "3.30"}}, "Corners 1x2": {"1": {"Marathon": "3.14", "1xbet": "2.98", "888Sport": "2.75", "Unibet": "2.75", "10Bet": "3.00", "ComeOn": "3.20", "bwin": "2.95", "WilliamHill": "2.62", "NordicBet": "2.60", "Betsson": "2.60", "Betway": "2.90"}, "X": {"Marathon": "8.30", "1xbet": "7.26", "888Sport": "7.50", "Unibet": "7.50", "10Bet": "6.25", "ComeOn": "6.75", "bwin": "6.50", "WilliamHill": "8.00", "NordicBet": "6.50", "Betsson": "6.50", "Betway": "7.50"}, "2": {"Marathon": "1.57", "1xbet": "1.68", "888Sport": "1.67", "Unibet": "1.67", "10Bet": "1.50", "ComeOn": "1.50", "bwin": "1.62", "WilliamHill": "1.62", "NordicBet": "1.78", "Betsson": "1.78", "Betway": "1.62"}}, "Clean Sheet - Away": {"Yes": {"bwin": "2.35", "Sportingbet": "2.35", "Betway": "2.40"}, "No": {"bwin": "1.53", "Sportingbet": "1.53", "Betway": "1.50"}}}}