[{"id": 192729, "competition_id": 5907, "full_name": "Kenneth Taylor", "first_name": "Kenneth", "last_name": "Taylor", "known_as": "Kenneth Taylor", "shorthand": "kenneth-taylor", "age": 19, "height": "0", "weight": "0", "league": "UEFA Euro U21 Championship Qualification", "league_type": "International", "season": "2023", "starting_year": 2020, "ending_year": 2023, "national_team_id": 0, "url": "https://footystats.org/players/netherlands/kenneth-taylor", "club_team_id": 666757, "club_team_2_id": -1, "position": "Midfielder", "minutes_played_overall": 167, "minutes_played_home": 49, "minutes_played_away": 118, "birthday": 1021507200, "nationality": "Netherlands", "continent": "", "appearances_overall": 4, "appearances_home": 2, "appearances_away": 2, "goals_overall": 0, "goals_home": 0, "goals_away": 0, "clean_sheets_home": 1, "clean_sheets_away": 1, "clean_sheets_overall": 2, "conceded_overall": 0, "conceded_home": 0, "conceded_away": 0, "assists_overall": 1, "assists_home": 0, "assists_away": 1, "penalty_goals": 0, "penalty_misses": 0, "penalty_success": -1, "goals_involved_per_90_overall": 0.54, "assists_per_90_overall": 0.54, "goals_per_90_overall": 0, "clean_sheets_per_overall": 50, "goals_per_90_home": 0, "goals_per_90_away": 0, "min_per_goal_overall": 0, "conceded_per_90_overall": 0, "min_per_conceded_overall": 0, "cards_overall": 0, "yellow_cards_overall": 0, "red_cards_overall": 0, "min_per_match": 42, "min_per_card_overall": 0, "min_per_assist_overall": 167, "cards_per_90_overall": 0, "rank_in_league_top_attackers": -1, "rank_in_league_top_midfielders": -1, "rank_in_league_top_defenders": -1, "rank_in_club_top_scorer": 9, "last_match_timestamp": 1636981200}, {"id": 192729, "competition_id": 6141, "full_name": "Kenneth Taylor", "first_name": "Kenneth", "last_name": "Taylor", "known_as": "Kenneth Taylor", "shorthand": "kenneth-taylor", "age": 19, "height": "0", "weight": "0", "league": "KNVB Cup", "league_type": "Cup", "season": "2021/2022", "starting_year": 2021, "ending_year": 2022, "national_team_id": 0, "url": "https://footystats.org/players/netherlands/kenneth-taylor", "club_team_id": 120, "club_team_2_id": -1, "position": "Midfielder", "minutes_played_overall": 180, "minutes_played_home": 180, "minutes_played_away": 0, "birthday": 1021507200, "nationality": "Netherlands", "continent": "eu", "appearances_overall": 2, "appearances_home": 2, "appearances_away": 0, "goals_overall": 1, "goals_home": 1, "goals_away": 0, "clean_sheets_home": 2, "clean_sheets_away": 0, "clean_sheets_overall": 2, "conceded_overall": 0, "conceded_home": 0, "conceded_away": 0, "assists_overall": 2, "assists_home": 2, "assists_away": 0, "penalty_goals": 0, "penalty_misses": 0, "penalty_success": -1, "goals_involved_per_90_overall": 1.5, "assists_per_90_overall": 1, "goals_per_90_overall": 0.5, "clean_sheets_per_overall": 100, "goals_per_90_home": 0.5, "goals_per_90_away": 0, "min_per_goal_overall": 180, "conceded_per_90_overall": 0, "min_per_conceded_overall": 0, "cards_overall": 0, "yellow_cards_overall": 0, "red_cards_overall": 0, "min_per_match": 90, "min_per_card_overall": 0, "min_per_assist_overall": 90, "cards_per_90_overall": 0, "rank_in_league_top_attackers": -1, "rank_in_league_top_midfielders": -1, "rank_in_league_top_defenders": -1, "rank_in_club_top_scorer": 5, "last_match_timestamp": 1642708800}, {"id": 192729, "competition_id": 5950, "full_name": "Kenneth Taylor", "first_name": "Kenneth", "last_name": "Taylor", "known_as": "Kenneth Taylor", "shorthand": "kenneth-taylor", "age": 19, "height": "0", "weight": "0", "league": "Eerste Divisie", "league_type": "Domestic League", "season": "2021/2022", "starting_year": 2021, "ending_year": 2022, "national_team_id": 0, "url": "https://footystats.org/players/netherlands/kenneth-taylor", "club_team_id": 400, "club_team_2_id": -1, "position": "Midfielder", "minutes_played_overall": 644, "minutes_played_home": 313, "minutes_played_away": 331, "birthday": 1021507200, "nationality": "Netherlands", "continent": "eu", "appearances_overall": 8, "appearances_home": 4, "appearances_away": 4, "goals_overall": 5, "goals_home": 3, "goals_away": 2, "clean_sheets_home": 1, "clean_sheets_away": 0, "clean_sheets_overall": 1, "conceded_overall": 11, "conceded_home": 7, "conceded_away": 4, "assists_overall": 1, "assists_home": 0, "assists_away": 1, "penalty_goals": 2, "penalty_misses": 0, "penalty_success": 100, "goals_involved_per_90_overall": 0.84, "assists_per_90_overall": 0.14, "goals_per_90_overall": 0.7, "clean_sheets_per_overall": 13, "goals_per_90_home": 0.86, "goals_per_90_away": 0.54, "min_per_goal_overall": 129, "conceded_per_90_overall": 1.54, "min_per_conceded_overall": 59, "cards_overall": 0, "yellow_cards_overall": 0, "red_cards_overall": 0, "min_per_match": 81, "min_per_card_overall": 0, "min_per_assist_overall": 644, "cards_per_90_overall": 0, "rank_in_league_top_attackers": 9, "rank_in_league_top_midfielders": 112, "rank_in_league_top_defenders": -1, "rank_in_club_top_scorer": 5, "last_match_timestamp": 1638817200}, {"id": 192729, "competition_id": 5951, "full_name": "Kenneth Taylor", "first_name": "Kenneth", "last_name": "Taylor", "known_as": "Kenneth Taylor", "shorthand": "kenneth-taylor", "age": 19, "height": "0", "weight": "0", "league": "Eredivisie", "league_type": "Domestic League", "season": "2021/2022", "starting_year": 2021, "ending_year": 2022, "national_team_id": 0, "url": "https://footystats.org/players/netherlands/kenneth-taylor", "club_team_id": 120, "club_team_2_id": -1, "position": "Midfielder", "minutes_played_overall": 97, "minutes_played_home": 59, "minutes_played_away": 38, "birthday": 1021507200, "nationality": "Netherlands", "continent": "eu", "appearances_overall": 6, "appearances_home": 3, "appearances_away": 3, "goals_overall": 1, "goals_home": 1, "goals_away": 0, "clean_sheets_home": 3, "clean_sheets_away": 3, "clean_sheets_overall": 6, "conceded_overall": 0, "conceded_home": 0, "conceded_away": 0, "assists_overall": 1, "assists_home": 1, "assists_away": 0, "penalty_goals": 0, "penalty_misses": 0, "penalty_success": -1, "goals_involved_per_90_overall": 1.86, "assists_per_90_overall": 0.93, "goals_per_90_overall": 0.93, "clean_sheets_per_overall": 100, "goals_per_90_home": 1.53, "goals_per_90_away": 0, "min_per_goal_overall": 97, "conceded_per_90_overall": 0, "min_per_conceded_overall": 0, "cards_overall": 0, "yellow_cards_overall": 0, "red_cards_overall": 0, "min_per_match": 16, "min_per_card_overall": 0, "min_per_assist_overall": 97, "cards_per_90_overall": 0, "rank_in_league_top_attackers": -1, "rank_in_league_top_midfielders": -1, "rank_in_league_top_defenders": -1, "rank_in_club_top_scorer": 16, "last_match_timestamp": 0}, {"id": 192729, "competition_id": 5952, "full_name": "Kenneth Taylor", "first_name": "Kenneth", "last_name": "Taylor", "known_as": "Kenneth Taylor", "shorthand": "kenneth-taylor", "age": 19, "height": "0", "weight": "0", "league": "Dutch Super Cup", "league_type": "Cup", "season": "2021/2022", "starting_year": 2021, "ending_year": 2022, "national_team_id": 0, "url": "https://footystats.org/players/netherlands/kenneth-taylor", "club_team_id": 120, "club_team_2_id": -1, "position": "Midfielder", "minutes_played_overall": 0, "minutes_played_home": 0, "minutes_played_away": 0, "birthday": 1021507200, "nationality": "Netherlands", "continent": "eu", "appearances_overall": 0, "appearances_home": 0, "appearances_away": 0, "goals_overall": 0, "goals_home": 0, "goals_away": 0, "clean_sheets_home": 0, "clean_sheets_away": 0, "clean_sheets_overall": 0, "conceded_overall": 0, "conceded_home": 0, "conceded_away": 0, "assists_overall": 0, "assists_home": 0, "assists_away": 0, "penalty_goals": 0, "penalty_misses": 0, "penalty_success": -1, "goals_involved_per_90_overall": 0, "assists_per_90_overall": 0, "goals_per_90_overall": 0, "clean_sheets_per_overall": 0, "goals_per_90_home": 0, "goals_per_90_away": 0, "min_per_goal_overall": 0, "conceded_per_90_overall": 0, "min_per_conceded_overall": 0, "cards_overall": 0, "yellow_cards_overall": 0, "red_cards_overall": 0, "min_per_match": 0, "min_per_card_overall": 0, "min_per_assist_overall": 0, "cards_per_90_overall": 0, "rank_in_league_top_attackers": -1, "rank_in_league_top_midfielders": -1, "rank_in_league_top_defenders": -1, "rank_in_club_top_scorer": -1, "last_match_timestamp": 0}, {"id": 192729, "competition_id": 5977, "full_name": "Kenneth Taylor", "first_name": "Kenneth", "last_name": "Taylor", "known_as": "Kenneth Taylor", "shorthand": "kenneth-taylor", "age": 19, "height": "0", "weight": "0", "league": "UEFA Champions League", "league_type": "Cup", "season": "2021/2022", "starting_year": 2021, "ending_year": 2022, "national_team_id": 0, "url": "https://footystats.org/players/netherlands/kenneth-taylor", "club_team_id": 120, "club_team_2_id": -1, "position": "Midfielder", "minutes_played_overall": 38, "minutes_played_home": 18, "minutes_played_away": 20, "birthday": 1021507200, "nationality": "Netherlands", "continent": "eu", "appearances_overall": 3, "appearances_home": 1, "appearances_away": 2, "goals_overall": 0, "goals_home": 0, "goals_away": 0, "clean_sheets_home": 0, "clean_sheets_away": 0, "clean_sheets_overall": 0, "conceded_overall": 1, "conceded_home": 1, "conceded_away": 0, "assists_overall": 0, "assists_home": 0, "assists_away": 0, "penalty_goals": 0, "penalty_misses": 0, "penalty_success": -1, "goals_involved_per_90_overall": 0, "assists_per_90_overall": 0, "goals_per_90_overall": 0, "clean_sheets_per_overall": 0, "goals_per_90_home": 0, "goals_per_90_away": 0, "min_per_goal_overall": 0, "conceded_per_90_overall": 2.37, "min_per_conceded_overall": 38, "cards_overall": 0, "yellow_cards_overall": 0, "red_cards_overall": 0, "min_per_match": 13, "min_per_card_overall": 0, "min_per_assist_overall": 0, "cards_per_90_overall": 0, "rank_in_league_top_attackers": -1, "rank_in_league_top_midfielders": -1, "rank_in_league_top_defenders": -1, "rank_in_club_top_scorer": 8, "last_match_timestamp": 0}, {"id": 192729, "competition_id": 4748, "full_name": "Kenneth Taylor", "first_name": "Kenneth", "last_name": "Taylor", "known_as": "Kenneth Taylor", "shorthand": "kenneth-taylor", "age": 19, "height": "0", "weight": "0", "league": "Eerste Divisie", "league_type": "Domestic League", "season": "2020/2021", "starting_year": 2020, "ending_year": 2021, "national_team_id": 0, "url": "https://footystats.org/players/netherlands/kenneth-taylor", "club_team_id": 400, "club_team_2_id": -1, "position": "Midfielder", "minutes_played_overall": 2545, "minutes_played_home": 1325, "minutes_played_away": 1220, "birthday": 1021507200, "nationality": "Netherlands", "continent": "eu", "appearances_overall": 29, "appearances_home": 15, "appearances_away": 14, "goals_overall": 7, "goals_home": 4, "goals_away": 3, "clean_sheets_home": 1, "clean_sheets_away": 1, "clean_sheets_overall": 2, "conceded_overall": 45, "conceded_home": 22, "conceded_away": 23, "assists_overall": 4, "assists_home": 1, "assists_away": 3, "penalty_goals": 4, "penalty_misses": 1, "penalty_success": 80, "goals_involved_per_90_overall": 0.39, "assists_per_90_overall": 0.14, "goals_per_90_overall": 0.25, "clean_sheets_per_overall": 7, "goals_per_90_home": 0.27, "goals_per_90_away": 0.22, "min_per_goal_overall": 364, "conceded_per_90_overall": 1.59, "min_per_conceded_overall": 57, "cards_overall": 5, "yellow_cards_overall": 5, "red_cards_overall": 0, "min_per_match": 88, "min_per_card_overall": 509, "min_per_assist_overall": 636, "cards_per_90_overall": 0.18, "rank_in_league_top_attackers": 99, "rank_in_league_top_midfielders": 137, "rank_in_league_top_defenders": -1, "rank_in_club_top_scorer": 3, "last_match_timestamp": 1620410400}, {"id": 192729, "competition_id": 4747, "full_name": "Kenneth Taylor", "first_name": "Kenneth", "last_name": "Taylor", "known_as": "Kenneth Taylor", "shorthand": "kenneth-taylor", "age": 19, "height": "0", "weight": "0", "league": "KNVB Cup", "league_type": "Cup", "season": "2020/2021", "starting_year": 2020, "ending_year": 2021, "national_team_id": 0, "url": "https://footystats.org/players/netherlands/kenneth-taylor", "club_team_id": 120, "club_team_2_id": -1, "position": "Midfielder", "minutes_played_overall": 0, "minutes_played_home": 0, "minutes_played_away": 0, "birthday": 1021507200, "nationality": "Netherlands", "continent": "eu", "appearances_overall": 0, "appearances_home": 0, "appearances_away": 0, "goals_overall": 0, "goals_home": 0, "goals_away": 0, "clean_sheets_home": 0, "clean_sheets_away": 0, "clean_sheets_overall": 0, "conceded_overall": 0, "conceded_home": 0, "conceded_away": 0, "assists_overall": 0, "assists_home": 0, "assists_away": 0, "penalty_goals": 0, "penalty_misses": 0, "penalty_success": -1, "goals_involved_per_90_overall": 0, "assists_per_90_overall": 0, "goals_per_90_overall": 0, "clean_sheets_per_overall": 0, "goals_per_90_home": 0, "goals_per_90_away": 0, "min_per_goal_overall": 0, "conceded_per_90_overall": 0, "min_per_conceded_overall": 0, "cards_overall": 0, "yellow_cards_overall": 0, "red_cards_overall": 0, "min_per_match": 0, "min_per_card_overall": 0, "min_per_assist_overall": 0, "cards_per_90_overall": 0, "rank_in_league_top_attackers": -1, "rank_in_league_top_midfielders": -1, "rank_in_league_top_defenders": -1, "rank_in_club_top_scorer": -1, "last_match_timestamp": 0}, {"id": 192729, "competition_id": 4746, "full_name": "Kenneth Taylor", "first_name": "Kenneth", "last_name": "Taylor", "known_as": "Kenneth Taylor", "shorthand": "kenneth-taylor", "age": 19, "height": "0", "weight": "0", "league": "Eredivisie", "league_type": "Domestic League", "season": "2020/2021", "starting_year": 2020, "ending_year": 2021, "national_team_id": 0, "url": "https://footystats.org/players/netherlands/kenneth-taylor", "club_team_id": 120, "club_team_2_id": -1, "position": "Midfielder", "minutes_played_overall": 116, "minutes_played_home": 72, "minutes_played_away": 44, "birthday": 1021507200, "nationality": "Netherlands", "continent": "eu", "appearances_overall": 3, "appearances_home": 2, "appearances_away": 1, "goals_overall": 0, "goals_home": 0, "goals_away": 0, "clean_sheets_home": 1, "clean_sheets_away": 0, "clean_sheets_overall": 1, "conceded_overall": 3, "conceded_home": 1, "conceded_away": 2, "assists_overall": 0, "assists_home": 0, "assists_away": 0, "penalty_goals": 0, "penalty_misses": 0, "penalty_success": -1, "goals_involved_per_90_overall": 0, "assists_per_90_overall": 0, "goals_per_90_overall": 0, "clean_sheets_per_overall": 33, "goals_per_90_home": 0, "goals_per_90_away": 0, "min_per_goal_overall": 0, "conceded_per_90_overall": 2.33, "min_per_conceded_overall": 39, "cards_overall": 2, "yellow_cards_overall": 1, "red_cards_overall": 1, "min_per_match": 39, "min_per_card_overall": 58, "min_per_assist_overall": 0, "cards_per_90_overall": 1.55, "rank_in_league_top_attackers": -1, "rank_in_league_top_midfielders": -1, "rank_in_league_top_defenders": -1, "rank_in_club_top_scorer": 22, "last_match_timestamp": 0}, {"id": 192729, "competition_id": 4693, "full_name": "Kenneth Taylor", "first_name": "Kenneth", "last_name": "Taylor", "known_as": "Kenneth Taylor", "shorthand": "kenneth-taylor", "age": 19, "height": "0", "weight": "0", "league": "UEFA Europa League", "league_type": "Cup", "season": "2020/2021", "starting_year": 2020, "ending_year": 2021, "national_team_id": 0, "url": "https://footystats.org/players/netherlands/kenneth-taylor", "club_team_id": 120, "club_team_2_id": -1, "position": "Midfielder", "minutes_played_overall": 0, "minutes_played_home": 0, "minutes_played_away": 0, "birthday": 1021507200, "nationality": "Netherlands", "continent": "eu", "appearances_overall": 0, "appearances_home": 0, "appearances_away": 0, "goals_overall": 0, "goals_home": 0, "goals_away": 0, "clean_sheets_home": 0, "clean_sheets_away": 0, "clean_sheets_overall": 0, "conceded_overall": 0, "conceded_home": 0, "conceded_away": 0, "assists_overall": 0, "assists_home": 0, "assists_away": 0, "penalty_goals": 0, "penalty_misses": 0, "penalty_success": -1, "goals_involved_per_90_overall": 0, "assists_per_90_overall": 0, "goals_per_90_overall": 0, "clean_sheets_per_overall": 0, "goals_per_90_home": 0, "goals_per_90_away": 0, "min_per_goal_overall": 0, "conceded_per_90_overall": 0, "min_per_conceded_overall": 0, "cards_overall": 0, "yellow_cards_overall": 0, "red_cards_overall": 0, "min_per_match": 0, "min_per_card_overall": 0, "min_per_assist_overall": 0, "cards_per_90_overall": 0, "rank_in_league_top_attackers": -1, "rank_in_league_top_midfielders": -1, "rank_in_league_top_defenders": -1, "rank_in_club_top_scorer": -1, "last_match_timestamp": 0}, {"id": 192729, "competition_id": 3808, "full_name": "Kenneth Taylor", "first_name": "Kenneth", "last_name": "Taylor", "known_as": "Kenneth Taylor", "shorthand": "kenneth-taylor", "age": 19, "height": "0", "weight": "0", "league": "UEFA Youth League", "league_type": "Cup", "season": "2019/2020", "starting_year": 2019, "ending_year": 2020, "national_team_id": 0, "url": "https://footystats.org/players/netherlands/kenneth-taylor", "club_team_id": 678845, "club_team_2_id": -1, "position": "Midfielder", "minutes_played_overall": 323, "minutes_played_home": 143, "minutes_played_away": 180, "birthday": 1021507200, "nationality": "Netherlands", "continent": "eu", "appearances_overall": 4, "appearances_home": 2, "appearances_away": 2, "goals_overall": 1, "goals_home": 0, "goals_away": 1, "clean_sheets_home": 1, "clean_sheets_away": 0, "clean_sheets_overall": 1, "conceded_overall": 5, "conceded_home": 1, "conceded_away": 4, "assists_overall": 1, "assists_home": 0, "assists_away": 1, "penalty_goals": 0, "penalty_misses": 0, "penalty_success": -1, "goals_involved_per_90_overall": 0.56, "assists_per_90_overall": 0.28, "goals_per_90_overall": 0.28, "clean_sheets_per_overall": 25, "goals_per_90_home": 0, "goals_per_90_away": 0.5, "min_per_goal_overall": 323, "conceded_per_90_overall": 1.39, "min_per_conceded_overall": 65, "cards_overall": 0, "yellow_cards_overall": 0, "red_cards_overall": 0, "min_per_match": 81, "min_per_card_overall": 0, "min_per_assist_overall": 323, "cards_per_90_overall": 0, "rank_in_league_top_attackers": 114, "rank_in_league_top_midfielders": 51, "rank_in_league_top_defenders": -1, "rank_in_club_top_scorer": 9, "last_match_timestamp": 1583244000}, {"id": 192729, "competition_id": 2273, "full_name": "Kenneth Taylor", "first_name": "Kenneth", "last_name": "Taylor", "known_as": "Kenneth Taylor", "shorthand": "kenneth-taylor", "age": 19, "height": "0", "weight": "0", "league": "Eerste Divisie", "league_type": "Domestic League", "season": "2019/2020", "starting_year": 2019, "ending_year": 2020, "national_team_id": 0, "url": "https://footystats.org/players/netherlands/kenneth-taylor", "club_team_id": 400, "club_team_2_id": -1, "position": "Midfielder", "minutes_played_overall": 996, "minutes_played_home": 566, "minutes_played_away": 430, "birthday": 1021507200, "nationality": "Netherlands", "continent": "eu", "appearances_overall": 19, "appearances_home": 10, "appearances_away": 9, "goals_overall": 0, "goals_home": 0, "goals_away": 0, "clean_sheets_home": 4, "clean_sheets_away": 2, "clean_sheets_overall": 6, "conceded_overall": 19, "conceded_home": 6, "conceded_away": 13, "assists_overall": 2, "assists_home": 1, "assists_away": 1, "penalty_goals": 0, "penalty_misses": 0, "penalty_success": -1, "goals_involved_per_90_overall": 0.18, "assists_per_90_overall": 0.18, "goals_per_90_overall": 0, "clean_sheets_per_overall": 32, "goals_per_90_home": 0, "goals_per_90_away": 0, "min_per_goal_overall": 0, "conceded_per_90_overall": 1.72, "min_per_conceded_overall": 52, "cards_overall": 1, "yellow_cards_overall": 1, "red_cards_overall": 0, "min_per_match": 52, "min_per_card_overall": 996, "min_per_assist_overall": 498, "cards_per_90_overall": 0.09, "rank_in_league_top_attackers": 298, "rank_in_league_top_midfielders": 88, "rank_in_league_top_defenders": -1, "rank_in_club_top_scorer": 35, "last_match_timestamp": 1583521200}, {"id": 192729, "competition_id": 4051, "full_name": "Kenneth Taylor", "first_name": "Kenneth", "last_name": "Taylor", "known_as": "Kenneth Taylor", "shorthand": "kenneth-taylor", "age": 19, "height": "0", "weight": "0", "league": "UEFA Youth League", "league_type": "Cup", "season": "2018/2019", "starting_year": 2018, "ending_year": 2019, "national_team_id": 0, "url": "https://footystats.org/players/netherlands/kenneth-taylor", "club_team_id": 678845, "club_team_2_id": -1, "position": "Midfielder", "minutes_played_overall": 183, "minutes_played_home": 86, "minutes_played_away": 97, "birthday": 1021507200, "nationality": "Netherlands", "continent": "eu", "appearances_overall": 4, "appearances_home": 2, "appearances_away": 2, "goals_overall": 1, "goals_home": 0, "goals_away": 1, "clean_sheets_home": 1, "clean_sheets_away": 0, "clean_sheets_overall": 1, "conceded_overall": 1, "conceded_home": 1, "conceded_away": 0, "assists_overall": 0, "assists_home": 0, "assists_away": 0, "penalty_goals": 0, "penalty_misses": 0, "penalty_success": -1, "goals_involved_per_90_overall": 0.49, "assists_per_90_overall": 0, "goals_per_90_overall": 0.49, "clean_sheets_per_overall": 25, "goals_per_90_home": 0, "goals_per_90_away": 0.93, "min_per_goal_overall": 183, "conceded_per_90_overall": 0.49, "min_per_conceded_overall": 183, "cards_overall": 0, "yellow_cards_overall": 0, "red_cards_overall": 0, "min_per_match": 46, "min_per_card_overall": 0, "min_per_assist_overall": 0, "cards_per_90_overall": 0, "rank_in_league_top_attackers": -1, "rank_in_league_top_midfielders": -1, "rank_in_league_top_defenders": -1, "rank_in_club_top_scorer": 5, "last_match_timestamp": 1544626800}, {"id": 192729, "competition_id": 3074, "full_name": "Kenneth Taylor", "first_name": "Kenneth", "last_name": "Taylor", "known_as": "Kenneth Taylor", "shorthand": "kenneth-taylor", "age": 19, "height": "0", "weight": "0", "league": "FIFA U17 World Cup", "league_type": "International", "season": "2019", "starting_year": 2019, "ending_year": 2019, "national_team_id": 0, "url": "https://footystats.org/players/netherlands/kenneth-taylor", "club_team_id": 675443, "club_team_2_id": -1, "position": "Midfielder", "minutes_played_overall": 449, "minutes_played_home": 287, "minutes_played_away": 162, "birthday": 1021507200, "nationality": "Netherlands", "continent": "", "appearances_overall": 6, "appearances_home": 4, "appearances_away": 2, "goals_overall": 0, "goals_home": 0, "goals_away": 0, "clean_sheets_home": 1, "clean_sheets_away": 0, "clean_sheets_overall": 1, "conceded_overall": 8, "conceded_home": 5, "conceded_away": 3, "assists_overall": 2, "assists_home": 2, "assists_away": 0, "penalty_goals": 0, "penalty_misses": 1, "penalty_success": 0, "goals_involved_per_90_overall": 0.4, "assists_per_90_overall": 0.4, "goals_per_90_overall": 0, "clean_sheets_per_overall": 17, "goals_per_90_home": 0, "goals_per_90_away": 0, "min_per_goal_overall": 0, "conceded_per_90_overall": 1.6, "min_per_conceded_overall": 56, "cards_overall": 0, "yellow_cards_overall": 0, "red_cards_overall": 0, "min_per_match": 75, "min_per_card_overall": 0, "min_per_assist_overall": 225, "cards_per_90_overall": 0, "rank_in_league_top_attackers": 74, "rank_in_league_top_midfielders": 11, "rank_in_league_top_defenders": -1, "rank_in_club_top_scorer": 13, "last_match_timestamp": 1574013600}, {"id": 192729, "competition_id": 1584, "full_name": "Kenneth Taylor", "first_name": "Kenneth", "last_name": "Taylor", "known_as": "Kenneth Taylor", "shorthand": "kenneth-taylor", "age": 19, "height": "0", "weight": "0", "league": "Eerste Divisie", "league_type": "Domestic League", "season": "2018/2019", "starting_year": 2018, "ending_year": 2019, "national_team_id": 0, "url": "https://footystats.org/players/netherlands/kenneth-taylor", "club_team_id": 400, "club_team_2_id": -1, "position": "Midfielder", "minutes_played_overall": 20, "minutes_played_home": 0, "minutes_played_away": 20, "birthday": 1021507200, "nationality": "Netherlands", "continent": "eu", "appearances_overall": 1, "appearances_home": 0, "appearances_away": 1, "goals_overall": 0, "goals_home": 0, "goals_away": 0, "clean_sheets_home": 0, "clean_sheets_away": 0, "clean_sheets_overall": 0, "conceded_overall": 0, "conceded_home": 0, "conceded_away": 0, "assists_overall": 0, "assists_home": 0, "assists_away": 0, "penalty_goals": 0, "penalty_misses": 0, "penalty_success": -1, "goals_involved_per_90_overall": 0, "assists_per_90_overall": 0, "goals_per_90_overall": 0, "clean_sheets_per_overall": 0, "goals_per_90_home": 0, "goals_per_90_away": 0, "min_per_goal_overall": 0, "conceded_per_90_overall": 0, "min_per_conceded_overall": 0, "cards_overall": 0, "yellow_cards_overall": 0, "red_cards_overall": 0, "min_per_match": 20, "min_per_card_overall": 0, "min_per_assist_overall": 0, "cards_per_90_overall": 0, "rank_in_league_top_attackers": -1, "rank_in_league_top_midfielders": -1, "rank_in_league_top_defenders": -1, "rank_in_club_top_scorer": 21, "last_match_timestamp": 0}]