[{"id": 156056, "competition_id": 6050, "full_name": "Thijs Oosting", "first_name": "Thijs", "last_name": "Oosting", "known_as": "Thijs Oosting", "shorthand": "thijs-oosting", "age": 21, "height": "0", "weight": "0", "league": "UEFA Europa Conference League", "league_type": "Cup", "season": "2021/2022", "starting_year": 2021, "ending_year": 2022, "national_team_id": 0, "url": "https://footystats.org/players/netherlands/thijs-oosting", "club_team_id": 378, "club_team_2_id": -1, "position": "Midfielder", "minutes_played_overall": 12, "minutes_played_home": 12, "minutes_played_away": 0, "birthday": 957225600, "nationality": "Netherlands", "continent": "eu", "appearances_overall": 1, "appearances_home": 1, "appearances_away": 0, "goals_overall": 1, "goals_home": 1, "goals_away": 0, "clean_sheets_home": 1, "clean_sheets_away": 0, "clean_sheets_overall": 1, "conceded_overall": 0, "conceded_home": 0, "conceded_away": 0, "assists_overall": 0, "assists_home": 0, "assists_away": 0, "penalty_goals": 0, "penalty_misses": 0, "penalty_success": -1, "goals_involved_per_90_overall": 7.5, "assists_per_90_overall": 0, "goals_per_90_overall": 7.5, "clean_sheets_per_overall": 100, "goals_per_90_home": 7.5, "goals_per_90_away": 0, "min_per_goal_overall": 12, "conceded_per_90_overall": 0, "min_per_conceded_overall": 0, "cards_overall": 0, "yellow_cards_overall": 0, "red_cards_overall": 0, "min_per_match": 12, "min_per_card_overall": 0, "min_per_assist_overall": 0, "cards_per_90_overall": 0, "rank_in_league_top_attackers": -1, "rank_in_league_top_midfielders": -1, "rank_in_league_top_defenders": -1, "rank_in_club_top_scorer": 4, "last_match_timestamp": 0}, {"id": 156056, "competition_id": 6218, "full_name": "Thijs Oosting", "first_name": "Thijs", "last_name": "Oosting", "known_as": "Thijs Oosting", "shorthand": "thijs-oosting", "age": 21, "height": "0", "weight": "0", "league": "UEFA Europa League", "league_type": "Cup", "season": "2021/2022", "starting_year": 2021, "ending_year": 2022, "national_team_id": 0, "url": "https://footystats.org/players/netherlands/thijs-oosting", "club_team_id": 378, "club_team_2_id": -1, "position": "Midfielder", "minutes_played_overall": 90, "minutes_played_home": 0, "minutes_played_away": 90, "birthday": 957225600, "nationality": "Netherlands", "continent": "eu", "appearances_overall": 1, "appearances_home": 0, "appearances_away": 1, "goals_overall": 0, "goals_home": 0, "goals_away": 0, "clean_sheets_home": 0, "clean_sheets_away": 0, "clean_sheets_overall": 0, "conceded_overall": 2, "conceded_home": 0, "conceded_away": 2, "assists_overall": 0, "assists_home": 0, "assists_away": 0, "penalty_goals": 0, "penalty_misses": 0, "penalty_success": -1, "goals_involved_per_90_overall": 0, "assists_per_90_overall": 0, "goals_per_90_overall": 0, "clean_sheets_per_overall": 0, "goals_per_90_home": 0, "goals_per_90_away": 0, "min_per_goal_overall": 0, "conceded_per_90_overall": 2, "min_per_conceded_overall": 45, "cards_overall": 0, "yellow_cards_overall": 0, "red_cards_overall": 0, "min_per_match": 90, "min_per_card_overall": 0, "min_per_assist_overall": 0, "cards_per_90_overall": 0, "rank_in_league_top_attackers": -1, "rank_in_league_top_midfielders": -1, "rank_in_league_top_defenders": -1, "rank_in_club_top_scorer": 15, "last_match_timestamp": 1629312300}, {"id": 156056, "competition_id": 6141, "full_name": "Thijs Oosting", "first_name": "Thijs", "last_name": "Oosting", "known_as": "Thijs Oosting", "shorthand": "thijs-oosting", "age": 21, "height": "0", "weight": "0", "league": "KNVB Cup", "league_type": "Cup", "season": "2021/2022", "starting_year": 2021, "ending_year": 2022, "national_team_id": 0, "url": "https://footystats.org/players/netherlands/thijs-oosting", "club_team_id": 378, "club_team_2_id": -1, "position": "Midfielder", "minutes_played_overall": 0, "minutes_played_home": 0, "minutes_played_away": 0, "birthday": 957225600, "nationality": "Netherlands", "continent": "eu", "appearances_overall": 0, "appearances_home": 0, "appearances_away": 0, "goals_overall": 0, "goals_home": 0, "goals_away": 0, "clean_sheets_home": 0, "clean_sheets_away": 0, "clean_sheets_overall": 0, "conceded_overall": 0, "conceded_home": 0, "conceded_away": 0, "assists_overall": 0, "assists_home": 0, "assists_away": 0, "penalty_goals": 0, "penalty_misses": 0, "penalty_success": -1, "goals_involved_per_90_overall": 0, "assists_per_90_overall": 0, "goals_per_90_overall": 0, "clean_sheets_per_overall": 0, "goals_per_90_home": 0, "goals_per_90_away": 0, "min_per_goal_overall": 0, "conceded_per_90_overall": 0, "min_per_conceded_overall": 0, "cards_overall": 0, "yellow_cards_overall": 0, "red_cards_overall": 0, "min_per_match": 0, "min_per_card_overall": 0, "min_per_assist_overall": 0, "cards_per_90_overall": 0, "rank_in_league_top_attackers": -1, "rank_in_league_top_midfielders": -1, "rank_in_league_top_defenders": -1, "rank_in_club_top_scorer": -1, "last_match_timestamp": 0}, {"id": 156056, "competition_id": 5950, "full_name": "Thijs Oosting", "first_name": "Thijs", "last_name": "Oosting", "known_as": "Thijs Oosting", "shorthand": "thijs-oosting", "age": 21, "height": "0", "weight": "0", "league": "Eerste Divisie", "league_type": "Domestic League", "season": "2021/2022", "starting_year": 2021, "ending_year": 2022, "national_team_id": 0, "url": "https://footystats.org/players/netherlands/thijs-oosting", "club_team_id": 1043, "club_team_2_id": -1, "position": "Midfielder", "minutes_played_overall": 662, "minutes_played_home": 282, "minutes_played_away": 380, "birthday": 957225600, "nationality": "Netherlands", "continent": "eu", "appearances_overall": 9, "appearances_home": 4, "appearances_away": 5, "goals_overall": 0, "goals_home": 0, "goals_away": 0, "clean_sheets_home": 1, "clean_sheets_away": 0, "clean_sheets_overall": 1, "conceded_overall": 7, "conceded_home": 2, "conceded_away": 5, "assists_overall": 2, "assists_home": 2, "assists_away": 0, "penalty_goals": 0, "penalty_misses": 0, "penalty_success": -1, "goals_involved_per_90_overall": 0.27, "assists_per_90_overall": 0.27, "goals_per_90_overall": 0, "clean_sheets_per_overall": 11, "goals_per_90_home": 0, "goals_per_90_away": 0, "min_per_goal_overall": 0, "conceded_per_90_overall": 0.95, "min_per_conceded_overall": 95, "cards_overall": 0, "yellow_cards_overall": 0, "red_cards_overall": 0, "min_per_match": 74, "min_per_card_overall": 0, "min_per_assist_overall": 331, "cards_per_90_overall": 0, "rank_in_league_top_attackers": 253, "rank_in_league_top_midfielders": 33, "rank_in_league_top_defenders": -1, "rank_in_club_top_scorer": 19, "last_match_timestamp": 1643050800}, {"id": 156056, "competition_id": 5951, "full_name": "Thijs Oosting", "first_name": "Thijs", "last_name": "Oosting", "known_as": "Thijs Oosting", "shorthand": "thijs-oosting", "age": 21, "height": "0", "weight": "0", "league": "Eredivisie", "league_type": "Domestic League", "season": "2021/2022", "starting_year": 2021, "ending_year": 2022, "national_team_id": 0, "url": "https://footystats.org/players/netherlands/thijs-oosting", "club_team_id": 378, "club_team_2_id": 381, "position": "Midfielder", "minutes_played_overall": 220, "minutes_played_home": 115, "minutes_played_away": 105, "birthday": 957225600, "nationality": "Netherlands", "continent": "eu", "appearances_overall": 4, "appearances_home": 2, "appearances_away": 2, "goals_overall": 2, "goals_home": 2, "goals_away": 0, "clean_sheets_home": 1, "clean_sheets_away": 0, "clean_sheets_overall": 1, "conceded_overall": 2, "conceded_home": 1, "conceded_away": 1, "assists_overall": 0, "assists_home": 0, "assists_away": 0, "penalty_goals": 0, "penalty_misses": 0, "penalty_success": -1, "goals_involved_per_90_overall": 0.82, "assists_per_90_overall": 0, "goals_per_90_overall": 0.82, "clean_sheets_per_overall": 25, "goals_per_90_home": 1.57, "goals_per_90_away": 0, "min_per_goal_overall": 110, "conceded_per_90_overall": 0.82, "min_per_conceded_overall": 110, "cards_overall": 0, "yellow_cards_overall": 0, "red_cards_overall": 0, "min_per_match": 55, "min_per_card_overall": 0, "min_per_assist_overall": 0, "cards_per_90_overall": 0, "rank_in_league_top_attackers": -1, "rank_in_league_top_midfielders": -1, "rank_in_league_top_defenders": -1, "rank_in_club_top_scorer": 4, "last_match_timestamp": 1644154200}, {"id": 156056, "competition_id": 4748, "full_name": "Thijs Oosting", "first_name": "Thijs", "last_name": "Oosting", "known_as": "Thijs Oosting", "shorthand": "thijs-oosting", "age": 21, "height": "0", "weight": "0", "league": "Eerste Divisie", "league_type": "Domestic League", "season": "2020/2021", "starting_year": 2020, "ending_year": 2021, "national_team_id": 0, "url": "https://footystats.org/players/netherlands/thijs-oosting", "club_team_id": 1043, "club_team_2_id": -1, "position": "Midfielder", "minutes_played_overall": 1311, "minutes_played_home": 681, "minutes_played_away": 630, "birthday": 957225600, "nationality": "Netherlands", "continent": "eu", "appearances_overall": 15, "appearances_home": 8, "appearances_away": 7, "goals_overall": 7, "goals_home": 4, "goals_away": 3, "clean_sheets_home": 0, "clean_sheets_away": 1, "clean_sheets_overall": 1, "conceded_overall": 35, "conceded_home": 22, "conceded_away": 13, "assists_overall": 5, "assists_home": 4, "assists_away": 1, "penalty_goals": 0, "penalty_misses": 0, "penalty_success": -1, "goals_involved_per_90_overall": 0.82, "assists_per_90_overall": 0.34, "goals_per_90_overall": 0.48, "clean_sheets_per_overall": 7, "goals_per_90_home": 0.53, "goals_per_90_away": 0.43, "min_per_goal_overall": 187, "conceded_per_90_overall": 2.4, "min_per_conceded_overall": 37, "cards_overall": 1, "yellow_cards_overall": 1, "red_cards_overall": 0, "min_per_match": 87, "min_per_card_overall": 1311, "min_per_assist_overall": 262, "cards_per_90_overall": 0.07, "rank_in_league_top_attackers": 24, "rank_in_league_top_midfielders": 22, "rank_in_league_top_defenders": -1, "rank_in_club_top_scorer": 3, "last_match_timestamp": 1610740800}, {"id": 156056, "competition_id": 4747, "full_name": "Thijs Oosting", "first_name": "Thijs", "last_name": "Oosting", "known_as": "Thijs Oosting", "shorthand": "thijs-oosting", "age": 21, "height": "0", "weight": "0", "league": "KNVB Cup", "league_type": "Cup", "season": "2020/2021", "starting_year": 2020, "ending_year": 2021, "national_team_id": 0, "url": "https://footystats.org/players/netherlands/thijs-oosting", "club_team_id": 378, "club_team_2_id": -1, "position": "Midfielder", "minutes_played_overall": 0, "minutes_played_home": 0, "minutes_played_away": 0, "birthday": 957225600, "nationality": "Netherlands", "continent": "eu", "appearances_overall": 0, "appearances_home": 0, "appearances_away": 0, "goals_overall": 0, "goals_home": 0, "goals_away": 0, "clean_sheets_home": 0, "clean_sheets_away": 0, "clean_sheets_overall": 0, "conceded_overall": 0, "conceded_home": 0, "conceded_away": 0, "assists_overall": 0, "assists_home": 0, "assists_away": 0, "penalty_goals": 0, "penalty_misses": 0, "penalty_success": -1, "goals_involved_per_90_overall": 0, "assists_per_90_overall": 0, "goals_per_90_overall": 0, "clean_sheets_per_overall": 0, "goals_per_90_home": 0, "goals_per_90_away": 0, "min_per_goal_overall": 0, "conceded_per_90_overall": 0, "min_per_conceded_overall": 0, "cards_overall": 0, "yellow_cards_overall": 0, "red_cards_overall": 0, "min_per_match": 0, "min_per_card_overall": 0, "min_per_assist_overall": 0, "cards_per_90_overall": 0, "rank_in_league_top_attackers": -1, "rank_in_league_top_midfielders": -1, "rank_in_league_top_defenders": -1, "rank_in_club_top_scorer": -1, "last_match_timestamp": 0}, {"id": 156056, "competition_id": 4746, "full_name": "Thijs Oosting", "first_name": "Thijs", "last_name": "Oosting", "known_as": "Thijs Oosting", "shorthand": "thijs-oosting", "age": 21, "height": "0", "weight": "0", "league": "Eredivisie", "league_type": "Domestic League", "season": "2020/2021", "starting_year": 2020, "ending_year": 2021, "national_team_id": 0, "url": "https://footystats.org/players/netherlands/thijs-oosting", "club_team_id": 378, "club_team_2_id": 386, "position": "Midfielder", "minutes_played_overall": 1177, "minutes_played_home": 633, "minutes_played_away": 544, "birthday": 957225600, "nationality": "Netherlands", "continent": "eu", "appearances_overall": 17, "appearances_home": 8, "appearances_away": 9, "goals_overall": 4, "goals_home": 3, "goals_away": 1, "clean_sheets_home": 2, "clean_sheets_away": 1, "clean_sheets_overall": 3, "conceded_overall": 22, "conceded_home": 9, "conceded_away": 13, "assists_overall": 3, "assists_home": 3, "assists_away": 0, "penalty_goals": 0, "penalty_misses": 0, "penalty_success": -1, "goals_involved_per_90_overall": 0.54, "assists_per_90_overall": 0.23, "goals_per_90_overall": 0.31, "clean_sheets_per_overall": 18, "goals_per_90_home": 0.43, "goals_per_90_away": 0.17, "min_per_goal_overall": 294, "conceded_per_90_overall": 1.68, "min_per_conceded_overall": 54, "cards_overall": 2, "yellow_cards_overall": 2, "red_cards_overall": 0, "min_per_match": 69, "min_per_card_overall": 589, "min_per_assist_overall": 392, "cards_per_90_overall": 0.15, "rank_in_league_top_attackers": 57, "rank_in_league_top_midfielders": 40, "rank_in_league_top_defenders": -1, "rank_in_club_top_scorer": 3, "last_match_timestamp": 1621168200}, {"id": 156056, "competition_id": 2273, "full_name": "Thijs Oosting", "first_name": "Thijs", "last_name": "Oosting", "known_as": "Thijs Oosting", "shorthand": "thijs-oosting", "age": 21, "height": "0", "weight": "0", "league": "Eerste Divisie", "league_type": "Domestic League", "season": "2019/2020", "starting_year": 2019, "ending_year": 2020, "national_team_id": 0, "url": "https://footystats.org/players/netherlands/thijs-oosting", "club_team_id": 1043, "club_team_2_id": -1, "position": "Midfielder", "minutes_played_overall": 2158, "minutes_played_home": 927, "minutes_played_away": 1231, "birthday": 957225600, "nationality": "Netherlands", "continent": "eu", "appearances_overall": 28, "appearances_home": 14, "appearances_away": 14, "goals_overall": 8, "goals_home": 4, "goals_away": 4, "clean_sheets_home": 1, "clean_sheets_away": 0, "clean_sheets_overall": 1, "conceded_overall": 49, "conceded_home": 14, "conceded_away": 35, "assists_overall": 4, "assists_home": 2, "assists_away": 2, "penalty_goals": 0, "penalty_misses": 1, "penalty_success": 0, "goals_involved_per_90_overall": 0.5, "assists_per_90_overall": 0.17, "goals_per_90_overall": 0.33, "clean_sheets_per_overall": 4, "goals_per_90_home": 0.39, "goals_per_90_away": 0.29, "min_per_goal_overall": 270, "conceded_per_90_overall": 2.04, "min_per_conceded_overall": 44, "cards_overall": 3, "yellow_cards_overall": 3, "red_cards_overall": 0, "min_per_match": 77, "min_per_card_overall": 719, "min_per_assist_overall": 540, "cards_per_90_overall": 0.13, "rank_in_league_top_attackers": 59, "rank_in_league_top_midfielders": 98, "rank_in_league_top_defenders": -1, "rank_in_club_top_scorer": 2, "last_match_timestamp": 1582916400}, {"id": 156056, "competition_id": 1584, "full_name": "Thijs Oosting", "first_name": "Thijs", "last_name": "Oosting", "known_as": "Thijs Oosting", "shorthand": "thijs-oosting", "age": 21, "height": "0", "weight": "0", "league": "Eerste Divisie", "league_type": "Domestic League", "season": "2018/2019", "starting_year": 2018, "ending_year": 2019, "national_team_id": 0, "url": "https://footystats.org/players/netherlands/thijs-oosting", "club_team_id": 1043, "club_team_2_id": -1, "position": "Midfielder", "minutes_played_overall": 78, "minutes_played_home": 54, "minutes_played_away": 24, "birthday": 957225600, "nationality": "Netherlands", "continent": "eu", "appearances_overall": 5, "appearances_home": 3, "appearances_away": 2, "goals_overall": 2, "goals_home": 1, "goals_away": 1, "clean_sheets_home": 2, "clean_sheets_away": 0, "clean_sheets_overall": 2, "conceded_overall": 1, "conceded_home": 1, "conceded_away": 0, "assists_overall": 0, "assists_home": 0, "assists_away": 0, "penalty_goals": 0, "penalty_misses": 0, "penalty_success": -1, "goals_involved_per_90_overall": 2.31, "assists_per_90_overall": 0, "goals_per_90_overall": 2.31, "clean_sheets_per_overall": 40, "goals_per_90_home": 1.67, "goals_per_90_away": 3.75, "min_per_goal_overall": 39, "conceded_per_90_overall": 1.15, "min_per_conceded_overall": 78, "cards_overall": 0, "yellow_cards_overall": 0, "red_cards_overall": 0, "min_per_match": 16, "min_per_card_overall": 0, "min_per_assist_overall": 0, "cards_per_90_overall": 0, "rank_in_league_top_attackers": -1, "rank_in_league_top_midfielders": -1, "rank_in_league_top_defenders": -1, "rank_in_club_top_scorer": 6, "last_match_timestamp": 0}, {"id": 156056, "competition_id": 179, "full_name": "Thijs Oosting", "first_name": "Thijs", "last_name": "Oosting", "known_as": "Thijs Oosting", "shorthand": "thijs-oosting", "age": 21, "height": "0", "weight": "0", "league": "Eerste Divisie", "league_type": "Domestic League", "season": "2017/2018", "starting_year": 2017, "ending_year": 2018, "national_team_id": 0, "url": "https://footystats.org/players/netherlands/thijs-oosting", "club_team_id": 1043, "club_team_2_id": -1, "position": "Midfielder", "minutes_played_overall": 0, "minutes_played_home": 0, "minutes_played_away": 0, "birthday": 957225600, "nationality": "Netherlands", "continent": "eu", "appearances_overall": 0, "appearances_home": 0, "appearances_away": 0, "goals_overall": 0, "goals_home": 0, "goals_away": 0, "clean_sheets_home": 0, "clean_sheets_away": 0, "clean_sheets_overall": 0, "conceded_overall": 0, "conceded_home": 0, "conceded_away": 0, "assists_overall": 0, "assists_home": 0, "assists_away": 0, "penalty_goals": 0, "penalty_misses": 0, "penalty_success": -1, "goals_involved_per_90_overall": 0, "assists_per_90_overall": 0, "goals_per_90_overall": 0, "clean_sheets_per_overall": 0, "goals_per_90_home": 0, "goals_per_90_away": 0, "min_per_goal_overall": 0, "conceded_per_90_overall": 0, "min_per_conceded_overall": 0, "cards_overall": 0, "yellow_cards_overall": 0, "red_cards_overall": 0, "min_per_match": 0, "min_per_card_overall": 0, "min_per_assist_overall": 0, "cards_per_90_overall": 0, "rank_in_league_top_attackers": -1, "rank_in_league_top_midfielders": -1, "rank_in_league_top_defenders": -1, "rank_in_club_top_scorer": -1, "last_match_timestamp": 0}]